utilpack/__init__.py
utilpack/core/__init__.py
utilpack/core/algorithm.py
utilpack/core/config.py
utilpack/core/data.py
utilpack/core/error.py
utilpack/core/image.py
utilpack/core/logger.py
utilpack/core/maths.py
utilpack/core/output.py
utilpack/core/py.conf
utilpack/core/singleton.py
utilpack/core/time.py
utilpack/framework/__init__.py
utilpack/framework/py_flask.py
utilpack/util/__init__.py
utilpack/util/image_util.py
utilpack/util/time_util.py
utilpack-2.3.3.dist-info/METADATA
utilpack-2.3.3.dist-info/WHEEL
utilpack-2.3.3.dist-info/top_level.txt
utilpack-2.3.3.dist-info/RECORD
